tally/__init__.py
tally/build.py
tally/build_defaults.py
tally/dataset.py
tally/decorators.py
tally/helpers.py
tally/options.py
tally/presentation.py
tally/sheet.py
tally/tally.py
datasmoothie_tally_client-0.50.dist-info/LICENSE
datasmoothie_tally_client-0.50.dist-info/METADATA
datasmoothie_tally_client-0.50.dist-info/WHEEL
datasmoothie_tally_client-0.50.dist-info/top_level.txt
datasmoothie_tally_client-0.50.dist-info/RECORD
