Metadata-Version: 2.1
Name: datasmoothie-tally-client
Version: 0.50
Summary: Python wrapper for the Tally API.
Home-page: https://github.com/datasmoothie/datasmoothie-tally-client
Author: Geir Freysson
Author-email: geir@datasmoothie.com
License: MIT
Keywords: surveys,market research,weighting,significance tests
Classifier: Programming Language :: Python :: 3
Classifier: License :: OSI Approved :: MIT License
Classifier: Operating System :: OS Independent
License-File: LICENSE
Requires-Dist: numpy
Requires-Dist: pandas
Requires-Dist: openpyxl
Requires-Dist: pillow
Requires-Dist: requests
